main/__init__.py
main/__init___test.yaml
main/app/__init__.py
main/app/app.py
main/app/app.yaml
main/app/app_test.yaml
main/plugin/__init__.py
main/plugin/app.py
main/plugin/app.yaml
main/plugin/app_test.yaml
main/process/__init__.py
main/process/casts/__init__.py
main/process/casts/app.py
main/process/casts/app.yml
main/process/casts/app_test.yml
main/process/casts/handle_casting.py
main/process/casts/handle_casting.yaml
main/process/casts/handle_casting_resource.py
main/process/casts/handle_casting_test.yml
main/process/casts/resource.py
main/process/checks/__init__.py
main/process/checks/app.py
main/process/checks/app.yml
main/process/checks/app_test.yml
main/process/checks/resource.py
main/process/environment/__init__.py
main/process/environment/app.py
main/process/environment/app.yml
main/process/environment/app_test.yaml
main/process/locations/__init__.py
main/process/locations/app.py
main/process/locations/app.yaml
main/process/locations/app_test.yml
main/process/nodes/__init__.py
main/process/nodes/app.py
main/process/nodes/app.yml
main/process/nodes/app_test.yml
main/process/nodes/combine.py
main/process/nodes/combine.yml
main/process/nodes/combine_test.yml
main/process/patches/__init__.py
main/process/patches/app.py
main/process/patches/app.yml
main/process/patches/app_test.yml
main/process/setup/__init__.py
main/process/setup/app.py
main/process/setup/app.yaml
main/process/setup/app_test.yaml
main/process/setup/resource.py
main/process/spies/__init__.py
main/process/spies/app.py
main/process/spies/app.yml
main/process/spies/app_test.yaml
main/process/spies/resource.py
main/utils/__init__.py
main/utils/get_config/__init__.py
main/utils/get_config/app.py
main/utils/get_config/app.yaml
main/utils/get_config/app_test.yaml
main/utils/get_module/__init__.py
main/utils/get_module/app.py
main/utils/get_module/app_test.yaml
main/utils/get_module/resource.py
main/utils/independent/__init__.py
main/utils/independent/app.py
main/utils/independent/app_test.yml
yaml_testing_framework-0.0.6.dist-info/LICENSE
yaml_testing_framework-0.0.6.dist-info/METADATA
yaml_testing_framework-0.0.6.dist-info/WHEEL
yaml_testing_framework-0.0.6.dist-info/entry_points.txt
yaml_testing_framework-0.0.6.dist-info/top_level.txt
yaml_testing_framework-0.0.6.dist-info/zip-safe
yaml_testing_framework-0.0.6.dist-info/RECORD
