Metadata-Version: 2.1
Name: yaml_testing_framework
Version: 0.0.6
Summary: A testing framework where tests are defined in YAML files
Home-page: https://github.com/fjemi/yaml-testing-framework
Author: Olufemi Jemilohun
Author-email: olufemi.jemilohun@gmail.com
License: MIT license
Keywords: pytest,yaml,testing
Classifier: Framework :: Pytest
Classifier: Programming Language :: Python
Classifier: Topic :: Software Development :: Testing
Classifier: Programming Language :: Python :: 3.7
Requires-Python: >=3.7
License-File: LICENSE
Requires-Dist: pytest
Requires-Dist: pyyaml >=6.0.0
Requires-Dist: nest-asyncio
